pylinkage/__init__.py
pylinkage/_types.py
pylinkage/exceptions.py
pylinkage/assur/__init__.py
pylinkage/assur/_types.py
pylinkage/assur/conversion.py
pylinkage/assur/decomposition.py
pylinkage/assur/graph.py
pylinkage/assur/groups.py
pylinkage/assur/hypergraph_conversion.py
pylinkage/assur/serialization.py
pylinkage/bridge/__init__.py
pylinkage/bridge/solver_conversion.py
pylinkage/geometry/__init__.py
pylinkage/geometry/core.py
pylinkage/geometry/secants.py
pylinkage/hypergraph/__init__.py
pylinkage/hypergraph/_types.py
pylinkage/hypergraph/components.py
pylinkage/hypergraph/conversion.py
pylinkage/hypergraph/core.py
pylinkage/hypergraph/graph.py
pylinkage/hypergraph/hierarchy.py
pylinkage/hypergraph/library.py
pylinkage/hypergraph/serialization.py
pylinkage/joints/__init__.py
pylinkage/joints/crank.py
pylinkage/joints/fixed.py
pylinkage/joints/joint.py
pylinkage/joints/prismatic.py
pylinkage/joints/revolute.py
pylinkage/joints/static.py
pylinkage/linkage/__init__.py
pylinkage/linkage/analysis.py
pylinkage/linkage/linkage.py
pylinkage/linkage/serialization.py
pylinkage/optimization/__init__.py
pylinkage/optimization/async_optimization.py
pylinkage/optimization/grid_search.py
pylinkage/optimization/particle_swarm.py
pylinkage/optimization/utils.py
pylinkage/optimization/collections/__init__.py
pylinkage/optimization/collections/agent.py
pylinkage/optimization/collections/mutable_agent.py
pylinkage/solver/__init__.py
pylinkage/solver/conversion.py
pylinkage/solver/joints.py
pylinkage/solver/simulation.py
pylinkage/solver/types.py
pylinkage/visualizer/__init__.py
pylinkage/visualizer/animated.py
pylinkage/visualizer/core.py
pylinkage/visualizer/drawsvg_viz.py
pylinkage/visualizer/plotly_viz.py
pylinkage/visualizer/pso_plots.py
pylinkage/visualizer/static.py
pylinkage/visualizer/symbols.py
pylinkage-0.7.0.dist-info/METADATA
pylinkage-0.7.0.dist-info/WHEEL
pylinkage-0.7.0.dist-info/licenses/LICENSE
pylinkage-0.7.0.dist-info/RECORD
