Metadata-Version: 2.4
Name: pylinkage
Version: 0.7.0
Summary: Build and optimize planar linkages using PSO
Project-URL: Homepage, https://hugofara.github.io/pylinkage/
Project-URL: Documentation, https://hugofara.github.io/pylinkage/
Project-URL: Repository, https://github.com/HugoFara/pylinkage
Project-URL: Changelog, https://github.com/hugofara/pylinkage/blob/main/CHANGELOG.md
Author-email: Hugo Farajallah <pylinkage@hugofara.net>
License: MIT License
License-File: LICENSE
Keywords: linkage,mechanism,optimization,particle swarm optimization
Classifier: Development Status :: 4 - Beta
Classifier: Environment :: Console
Classifier: Intended Audience :: End Users/Desktop
Classifier: Intended Audience :: Science/Research
Classifier: Operating System :: OS Independent
Classifier: Programming Language :: Python :: 3
Classifier: Programming Language :: Python :: 3.10
Classifier: Programming Language :: Python :: 3.11
Classifier: Programming Language :: Python :: 3.12
Classifier: Programming Language :: Python :: 3.13
Classifier: Programming Language :: Python :: 3.14
Classifier: Topic :: Scientific/Engineering
Classifier: Topic :: Scientific/Engineering :: Artificial Intelligence
Requires-Python: >=3.10
Requires-Dist: drawsvg>=2.4.0
Requires-Dist: matplotlib>=3.3.4
Requires-Dist: numba>=0.60.0
Requires-Dist: numpy>=1.20.2
Requires-Dist: plotly>=6.5.0
Requires-Dist: pyswarms>=1.3.0
Requires-Dist: tqdm>=4.40.0
Provides-Extra: dev
Requires-Dist: hypothesis>=6.0.0; extra == 'dev'
Requires-Dist: mypy>=1.0.0; extra == 'dev'
Requires-Dist: pytest-cov>=4.0.0; extra == 'dev'
Requires-Dist: pytest>=7.0.0; extra == 'dev'
Requires-Dist: ruff>=0.4.0; extra == 'dev'
Provides-Extra: docs
Requires-Dist: myst-parser>=3.0.1; extra == 'docs'
Requires-Dist: sphinx-rtd-theme>=2.0.0; extra == 'docs'
Requires-Dist: sphinx>=7.4.2; extra == 'docs'
